northrend/__init__.py
northrend/commons/__init__.py
northrend/commons/time.py
northrend/data/__init__.py
northrend/data/features_engineer/__init__.py
northrend/data/features_engineer/nearest_neighbors.py
northrend/data/pandas_xtend/__init__.py
northrend/data/pandas_xtend/commons.py
northrend/data/pandas_xtend/describe.py
northrend/data/pandas_xtend/df.py
northrend/data/pandas_xtend/outlier.py
northrend/data/seaborn_xtend/__init__.py
northrend/data/seaborn_xtend/dist.py
northrend/data/sklearn_xtend/__init__.py
northrend/data/sklearn_xtend/pipeline/__init__.py
northrend/data/sklearn_xtend/pipeline/feature_names.py
northrend-1.0.2.dist-info/LICENSE
northrend-1.0.2.dist-info/METADATA
northrend-1.0.2.dist-info/WHEEL
northrend-1.0.2.dist-info/top_level.txt
northrend-1.0.2.dist-info/RECORD
